[{"name":"FlutterPop"},{"name":"RainbowPowerGirl","changedToAt":1438338530000},{"name":"Sassyrainbowfox","changedToAt":1443444978000},{"name":"Dinogirl44","changedToAt":1452003755000},{"name":"Wolfgirl33","changedToAt":1454702291000},{"name":"Bunbun66","changedToAt":1461952052000},{"name":"KawaiiKitten44","changedToAt":1464599210000},{"name":"Little_Emma44","changedToAt":1470042858000},{"name":"_Kitty_YT","changedToAt":1495213447000},{"name":"_GeekGirlDemon_","changedToAt":1535485850000},{"name":"emmaexists2","changedToAt":1606341480000}]