[{"name":"PVPBattler306"},{"name":"TannerTag306","changedToAt":1530057871000},{"name":"ii_MelonLemon_ii","changedToAt":1532699726000},{"name":"Lazer_Tech","changedToAt":1535385368000},{"name":"LuicidNation","changedToAt":1538262542000},{"name":"OGYT","changedToAt":1541113118000},{"name":"iLike_Ls","changedToAt":1543894107000},{"name":"KKMimicial","changedToAt":1547771926000},{"name":"KKBry6362","changedToAt":1562184394000},{"name":"Xafaa","changedToAt":1564779516000},{"name":"Potentiql","changedToAt":1567389194000},{"name":"Tyik","changedToAt":1570129527000},{"name":"Cqntent","changedToAt":1577044189000},{"name":"cafess","changedToAt":1579664412000},{"name":"unhandsomee","changedToAt":1583632318000},{"name":"communitave","changedToAt":1586831667000},{"name":"Outnames","changedToAt":1590685541000},{"name":"1_xz","changedToAt":1593355075000},{"name":"largebrains","changedToAt":1598566515000},{"name":"hyrdate","changedToAt":1604100414000},{"name":"pegh","changedToAt":1606883950000},{"name":"amuzingly","changedToAt":1620605781000},{"name":"angiexox","changedToAt":1628996182000},{"name":"sixteneer","changedToAt":1632067354000}]