[{"name":"XxHeyItsFirexX"},{"name":"MidnightDaWolf","changedToAt":1498637261000},{"name":"WolfieDaWerewolf","changedToAt":1503478279000},{"name":"GirlzCanGame","changedToAt":1508186739000},{"name":"HeidiGamez43191","changedToAt":1511340608000},{"name":"HeidiWills101","changedToAt":1513942172000},{"name":"_Emo_Gamer_","changedToAt":1519363023000},{"name":"HeidiLouiseYT","changedToAt":1539312871000},{"name":"Heidi_Louise","changedToAt":1564791976000},{"name":"symbolicmoon","changedToAt":1576056161000},{"name":"dmasbus","changedToAt":1586691116000},{"name":"rblurrr","changedToAt":1606562444000},{"name":"bblurie","changedToAt":1624441420000}]