[{"name":"Trinity2013"},{"name":"DarkNinja2015","changedToAt":1426814760000},{"name":"DarkKiller2015","changedToAt":1430887580000},{"name":"DarkNinja2015","changedToAt":1433988362000},{"name":"Trinity2013","changedToAt":1439153735000},{"name":"DarkNinja2015","changedToAt":1447743947000},{"name":"DarkNinja2016","changedToAt":1452224461000},{"name":"The_DarkAssassin","changedToAt":1484546779000},{"name":"Trinity2013","changedToAt":1497051873000},{"name":"Darkened_Heart","changedToAt":1510983993000},{"name":"The_GoldenHeart","changedToAt":1514626215000}]