[{"name":"MCSA5"},{"name":"Xx_Jay_xX","changedToAt":1514778112000},{"name":"_Derpy_Wolfy_","changedToAt":1531152431000},{"name":"TofuWasHere","changedToAt":1546828907000},{"name":"V2Skeppy","changedToAt":1551148421000},{"name":"TofuWasHere","changedToAt":1553989488000},{"name":"DauntlessWasHere","changedToAt":1558039213000},{"name":"lonely_joseph","changedToAt":1561008563000},{"name":"standout_","changedToAt":1570057069000},{"name":"fatoMan","changedToAt":1573081337000},{"name":"Fear_is_my_wifey","changedToAt":1576883583000},{"name":"Gaybersucs","changedToAt":1582931880000},{"name":"ItzClassy","changedToAt":1586473925000},{"name":"justclassy","changedToAt":1589931173000},{"name":"classy__fdsf","changedToAt":1599539907000},{"name":"classyjust","changedToAt":1604083517000},{"name":"classych1c","changedToAt":1650840594601}]