[{"name":"MarcusLeoDaniel"},{"name":"WotEvenIsLife","changedToAt":1522179124000},{"name":"_Sparkee_","changedToAt":1566955131000},{"name":"shparkee","changedToAt":1579540220000},{"name":"nigna","changedToAt":1585202035000},{"name":"Ishmuck","changedToAt":1588351105000},{"name":"CRACKINS","changedToAt":1590989684000},{"name":"Trazi","changedToAt":1593759110000},{"name":"Marcun","changedToAt":1596505939000},{"name":"penguinslide554","changedToAt":1604680803000},{"name":"Marcun","changedToAt":1607296212000},{"name":"jimmyjimo","changedToAt":1655327805711},{"name":"MARCUN","changedToAt":1658206421353}]