[{"name":"ayato1026"},{"name":"HP___4","changedToAt":1493119204000},{"name":"RegenFrog","changedToAt":1495793146000},{"name":"XXXXXXXXvideo","changedToAt":1499602769000},{"name":"HideOfLeviathan","changedToAt":1503105692000},{"name":"FadeGuilty","changedToAt":1506251615000},{"name":"VapeloadShumaww","changedToAt":1509177281000},{"name":"_yuk1bon","changedToAt":1512135025000},{"name":"yucky_Q","changedToAt":1537765150000},{"name":"Liefd","changedToAt":1541758656000},{"name":"MainMC","changedToAt":1545906011000},{"name":"yukibonDAZO","changedToAt":1548553587000},{"name":"Loaz","changedToAt":1551502185000}]