[{"name":"Max_Box02"},{"name":"heathcliff__","changedToAt":1500742285000},{"name":"mythicalwobblie","changedToAt":1504701454000},{"name":"HUsoldier01","changedToAt":1509090173000},{"name":"HowDoYouHit","changedToAt":1521357886000},{"name":"TenAM","changedToAt":1530304621000},{"name":"HUsoldier01","changedToAt":1536190128000},{"name":"LionHeart_AB","changedToAt":1553709904000},{"name":"HUsoldier01","changedToAt":1560219992000},{"name":"robloo","changedToAt":1578079075000},{"name":"AsianGirlNazty","changedToAt":1595060160000},{"name":"HUsoldier1","changedToAt":1607219756000}]