[{"name":"lavamasterxxx"},{"name":"MysticFirez","changedToAt":1520790425000},{"name":"TheMysticFirez","changedToAt":1526062344000},{"name":"xXMysticFirezXx","changedToAt":1529073426000},{"name":"MysticFirez","changedToAt":1531781244000},{"name":"MYSTICFIREZ","changedToAt":1534460821000},{"name":"MysticFirez","changedToAt":1555769527000},{"name":"MysticalDescent","changedToAt":1559858717000},{"name":"HEYEYEYEYEYEYEYE","changedToAt":1562964375000},{"name":"MysticalDescent","changedToAt":1565734117000},{"name":"God_Of_Skywars","changedToAt":1569883388000},{"name":"MysticFirez","changedToAt":1572562719000},{"name":"MysticChristmas","changedToAt":1575419149000},{"name":"MysticFirez","changedToAt":1578011859000},{"name":"Mystilteinn","changedToAt":1581637007000},{"name":"Descentof","changedToAt":1585069810000},{"name":"MysticFirez","changedToAt":1587738556000},{"name":"Descentof","changedToAt":1590348155000},{"name":"Determinati0n","changedToAt":1593028711000},{"name":"ilyLumine","changedToAt":1602200378000},{"name":"_keqing","changedToAt":1607997206000},{"name":"QiQiLess","changedToAt":1611760947000},{"name":"_Echidna__","changedToAt":1614380622000},{"name":"peaceowo","changedToAt":1617055418000},{"name":"xiyotaka","changedToAt":1640111947000},{"name":"NotPeace","changedToAt":1653242881713}]