[{"name":"XXxFazeGamezxXX"},{"name":"NoHaxJust_PvP","changedToAt":1451414165000},{"name":"AZombieInASuit","changedToAt":1454025069000},{"name":"Buttered_Pancake","changedToAt":1457208168000},{"name":"X_Impossible_X","changedToAt":1459988123000},{"name":"CaterpillarJr","changedToAt":1462620283000},{"name":"JoeyyMC","changedToAt":1465300920000},{"name":"PBAndJoey","changedToAt":1467906700000},{"name":"JoeyDEA","changedToAt":1470584530000},{"name":"PBAndJoey","changedToAt":1473195045000},{"name":"Overqted","changedToAt":1475800130000},{"name":"Zyphorix","changedToAt":1478609696000},{"name":"Jozoo","changedToAt":1482185054000},{"name":"exprr","changedToAt":1574129369000},{"name":"druhg","changedToAt":1577507577000},{"name":"ignWater","changedToAt":1598077189000},{"name":"Culion","changedToAt":1601065938000},{"name":"autopilots","changedToAt":1616174580000},{"name":"autoHV","changedToAt":1625025682661},{"name":"k1ttyb0y","changedToAt":1627804941276},{"name":"Autorin","changedToAt":1630772954391},{"name":"JayjaysWife","changedToAt":1635093323305},{"name":"RASPUTINPVP","changedToAt":1642272640589},{"name":"ilyNexus","changedToAt":1653697946152},{"name":"Zyphorix","changedToAt":1657486908440}]