[{"name":"Kaoer"},{"name":"Karambicik","changedToAt":1504456848000},{"name":"Aweczekkk","changedToAt":1512302836000},{"name":"Czuupss","changedToAt":1514925900000},{"name":"MehmetcikProo","changedToAt":1517582593000},{"name":"Narcyzz","changedToAt":1520263001000},{"name":"Yebiemietoo","changedToAt":1528289752000},{"name":"czuxikkkk","changedToAt":1539355588000},{"name":"xa3yo_","changedToAt":1541977696000},{"name":"https_kielak","changedToAt":1545323077000},{"name":"rafonixv2","changedToAt":1562597879000},{"name":"arpel2","changedToAt":1575396578000},{"name":"h11s","changedToAt":1578343426000},{"name":"Neira_","changedToAt":1588072218000},{"name":"h1ssss","changedToAt":1605123461000},{"name":"zuz1a__","changedToAt":1616543803000},{"name":"haessss","changedToAt":1637178655000}]