[{"name":"StumpedB"},{"name":"StumpedBee","changedToAt":1567360497000},{"name":"_sbee","changedToAt":1584848116000},{"name":"sbee_","changedToAt":1587852256000},{"name":"Stump3d","changedToAt":1591384510000},{"name":"Orbik","changedToAt":1594110836000},{"name":"qorb","changedToAt":1605158270000},{"name":"ChildJeanius","changedToAt":1617410562000},{"name":"CharlisLeftToe","changedToAt":1621843852000},{"name":"XxDat_Wolf_xd_xX","changedToAt":1624438037000},{"name":"fa1ryshart","changedToAt":1630216901000},{"name":"tomasleeftcek","changedToAt":1640679606000}]