[{"name":"BrockBacca"},{"name":"bananacheeks123","changedToAt":1456261335000},{"name":"BrockBacca","changedToAt":1459264095000},{"name":"TBNRfrags_YT","changedToAt":1462565604000},{"name":"TBNR_pinksheep","changedToAt":1465161059000},{"name":"NoHaxJustStewie","changedToAt":1469736073000},{"name":"BrockBacca","changedToAt":1473972957000},{"name":"DerpHamburger123","changedToAt":1481421282000},{"name":"CheesyButtcrack4","changedToAt":1504730304000},{"name":"CrispierBacon","changedToAt":1510883479000},{"name":"MarjanPlayz2","changedToAt":1514245458000},{"name":"CrispierBacon","changedToAt":1516916002000}]