[{"name":"A_Duone"},{"name":"WinSeo","changedToAt":1473593802000},{"name":"A_Duone","changedToAt":1476249156000},{"name":"GangChul","changedToAt":1480752224000},{"name":"Kangchul_Game","changedToAt":1483436148000},{"name":"BJ_Kangchul","changedToAt":1487227898000},{"name":"Kangcheol","changedToAt":1491046351000},{"name":"kc5383","changedToAt":1493650230000},{"name":"Yeop_","changedToAt":1497619693000},{"name":"WonChicken","changedToAt":1549522776000},{"name":"YEOP_","changedToAt":1564574743000},{"name":"Wonchicken","changedToAt":1585139946000}]