[{"name":"AssoDePicche"},{"name":"Paradyse","changedToAt":1423317426000},{"name":"ShawneeIT","changedToAt":1437504371000},{"name":"mariogieri","changedToAt":1457367495000},{"name":"MrM4r10","changedToAt":1469710119000},{"name":"MrMarjo","changedToAt":1472660170000},{"name":"MrMario_Games","changedToAt":1475845679000},{"name":"am_ireig","changedToAt":1478475283000},{"name":"Mario_Mojang","changedToAt":1481188648000},{"name":"Charltof","changedToAt":1492883749000},{"name":"WotbAyh","changedToAt":1499515707000},{"name":"KjNG","changedToAt":1503334348000},{"name":"tullio2001","changedToAt":1532871018000},{"name":"_xXDexter1420Xx_","changedToAt":1599437579000}]