[{"name":"Manfred56"},{"name":"Yana_6","changedToAt":1477752672000},{"name":"SrGalleticaYT","changedToAt":1483328718000},{"name":"TFB_ZaaiDaaX_7u7","changedToAt":1485958538000},{"name":"VioletBlack_7u7","changedToAt":1488672377000},{"name":"VioltexOne","changedToAt":1491401984000},{"name":"TheGuido7u7","changedToAt":1494546879000},{"name":"HailZaai","changedToAt":1498332439000},{"name":"ImDeep_","changedToAt":1505768333000},{"name":"Obscuridad","changedToAt":1511027109000},{"name":"NekoJR_","changedToAt":1513973655000},{"name":"Manfred56","changedToAt":1562830188000},{"name":"M00N_MAN","changedToAt":1569165008000},{"name":"Bumble_Door","changedToAt":1642889703000}]