[{"name":"bboony"},{"name":"ynobb","changedToAt":1423046743000},{"name":"bboony","changedToAt":1425690405000},{"name":"PartyWarrior","changedToAt":1429404955000},{"name":"kobboony","changedToAt":1432432895000},{"name":"aimbot_hax","changedToAt":1435451714000},{"name":"bboony","changedToAt":1438478760000},{"name":"fishymod","changedToAt":1442709413000},{"name":"bboony","changedToAt":1445412803000},{"name":"FT_alpa03","changedToAt":1472352374000},{"name":"bboony","changedToAt":1482741435000},{"name":"JakePaulFeminist","changedToAt":1502240257000},{"name":"Bass_Pro_Shop_","changedToAt":1562186647000},{"name":"rref_","changedToAt":1611354857000}]