[{"name":"YOLOSWAGLICIOUS"},{"name":"HacksKid","changedToAt":1612613079045},{"name":"YOLOSWAGLICIOUS","changedToAt":1615542956940},{"name":"HacksKid","changedToAt":1621419229405},{"name":"YOLOSWAGLICIOUS","changedToAt":1626008871659},{"name":"HacksKid","changedToAt":1628831947306},{"name":"YOLOSWAGLICIOUS","changedToAt":1631854865862},{"name":"Zfye","changedToAt":1637571672265},{"name":"YOLOSWAGLICIOUS","changedToAt":1643271066537},{"name":"HacksKid","changedToAt":1650263980712},{"name":"TarFux","changedToAt":1653393165633},{"name":"Yoloswaglicious","changedToAt":1656005862389},{"name":"Veraze","changedToAt":1661069939486}]