[{"name":"JackEndPlay"},{"name":"xMrJonas1337","changedToAt":1423062706000},{"name":"NyGGuSSeK","changedToAt":1425664558000},{"name":"NoCraftPL","changedToAt":1435499832000},{"name":"TheMasterKrzychu","changedToAt":1438097244000},{"name":"xDzano1997","changedToAt":1441119985000},{"name":"xEvovskyy","changedToAt":1448635268000},{"name":"xDzano1337","changedToAt":1454844062000},{"name":"70stick","changedToAt":1459521612000},{"name":"AleTuJebieSkunem","changedToAt":1462562270000},{"name":"AleJebieSkunem","changedToAt":1471283476000},{"name":"oprycha","changedToAt":1494339554000},{"name":"poka_pi3roga","changedToAt":1498739073000}]