[{"name":"yuu_1349"},{"name":"ItsYuuri","changedToAt":1430667280000},{"name":"ItzYuuri","changedToAt":1433600608000},{"name":"iTheYuuriN","changedToAt":1436273806000},{"name":"ItsYuuri","changedToAt":1438943097000},{"name":"Yufaly","changedToAt":1450584688000},{"name":"Yfl","changedToAt":1459426120000},{"name":"Yufaly","changedToAt":1462185207000},{"name":"Shapely","changedToAt":1470840159000},{"name":"Peint","changedToAt":1474153923000},{"name":"Coldcase","changedToAt":1476758192000},{"name":"K23d","changedToAt":1481079620000},{"name":"TRAPPIST1","changedToAt":1487841840000},{"name":"Sylphic","changedToAt":1494149997000},{"name":"Nautilus1800","changedToAt":1502255374000},{"name":"JeanneAlterX","changedToAt":1526637281000},{"name":"AlterX","changedToAt":1540729377000},{"name":"19Alice","changedToAt":1543323490000},{"name":"Yufaly","changedToAt":1557990341000}]