[{"name":"cxVeronika"},{"name":"lmperfection","changedToAt":1458436289000},{"name":"Kwiatkowski","changedToAt":1461199355000},{"name":"PossiblyVeronika","changedToAt":1469598222000},{"name":"Veronikaaa","changedToAt":1472526605000},{"name":"scooski","changedToAt":1477615479000},{"name":"Scooski","changedToAt":1480889953000},{"name":"PshhVeronika","changedToAt":1484013670000},{"name":"MeIoxy","changedToAt":1504508060000},{"name":"Scooski","changedToAt":1512282393000},{"name":"hoenst","changedToAt":1550427147000},{"name":"JeaIousy","changedToAt":1553609885000},{"name":"hoenst","changedToAt":1556293349000},{"name":"touchinq","changedToAt":1559868377000},{"name":"Heavenously","changedToAt":1566881116000},{"name":"unkissed","changedToAt":1581125282000}]