[{"name":"Rodrigo_PiViPi"},{"name":"CaroIsinhaSG","changedToAt":1432248228000},{"name":"Mercenari_","changedToAt":1434863287000},{"name":"KennyS_God","changedToAt":1437744678000},{"name":"Mercenari_","changedToAt":1441947033000},{"name":"_Mercenari","changedToAt":1449088207000},{"name":"GabiCherry","changedToAt":1455700849000},{"name":"Mercenari","changedToAt":1458860067000},{"name":"RodrigoHz","changedToAt":1504654056000},{"name":"heafty18","changedToAt":1522781176000},{"name":"RDGXITADO","changedToAt":1525571997000},{"name":"Mercenari","changedToAt":1528299388000},{"name":"RODMANDRAKE","changedToAt":1562434091000},{"name":"DaddyFinishw","changedToAt":1565895842000},{"name":"rebotiing","changedToAt":1568493171000},{"name":"Mercenari","changedToAt":1571121637000}]