[{"name":"brawler12"},{"name":"brawler14","changedToAt":1528861340000},{"name":"Luciel14","changedToAt":1532260299000},{"name":"KyuubiFox14","changedToAt":1538291603000},{"name":"HowlingKitsune","changedToAt":1540904821000},{"name":"BloodyOrgans","changedToAt":1551863568000},{"name":"HowlingKitsune","changedToAt":1554505538000},{"name":"EnderHowling","changedToAt":1557387854000},{"name":"DustyFlare","changedToAt":1562751526000},{"name":"My5oulisDead","changedToAt":1568294596000},{"name":"Merry5oul","changedToAt":1575042723000},{"name":"My5oulisDead","changedToAt":1577669595000},{"name":"ReSoul","changedToAt":1589706438000},{"name":"SH4LLOW","changedToAt":1624016494000},{"name":"ReSouless","changedToAt":1633176502000},{"name":"ReSoul","changedToAt":1642900392000}]