[{"name":"Ninja31GT"},{"name":"GalaxyCraft_GC","changedToAt":1452139173000},{"name":"HeyItzNoah","changedToAt":1454779161000},{"name":"LukasDoesMCx","changedToAt":1457390471000},{"name":"CoyoteLx","changedToAt":1460164562000},{"name":"iiCrypticXx_","changedToAt":1462761860000},{"name":"xMythicalNight","changedToAt":1465504744000},{"name":"Kxyden_","changedToAt":1468126559000},{"name":"_Clxckwork","changedToAt":1473207835000},{"name":"TwentyOneMuffinz","changedToAt":1476760752000},{"name":"Unicornz_AreReal","changedToAt":1481489519000},{"name":"SkyXDanccer","changedToAt":1484889697000},{"name":"ThisNameIsDumb","changedToAt":1487541718000},{"name":"rylan_exe","changedToAt":1490250444000},{"name":"UnicornFartz_","changedToAt":1492883728000},{"name":"AyyItzRy","changedToAt":1495499195000},{"name":"xEmpyreusxx","changedToAt":1498151125000},{"name":"53L","changedToAt":1501355093000},{"name":"54H","changedToAt":1508093282000}]