[{"name":"StarGirl_2003"},{"name":"SkylerLP","changedToAt":1501449305000},{"name":"Xx_Rainimator_xX","changedToAt":1518804673000},{"name":"_Rainimator_","changedToAt":1521837306000},{"name":"xRainimator","changedToAt":1536520122000},{"name":"Radapedaxa","changedToAt":1545065411000},{"name":"ItzmeChizzy","changedToAt":1570106085000},{"name":"xRainimator","changedToAt":1577197532000},{"name":"An9elDust","changedToAt":1586397309000},{"name":"Hushke","changedToAt":1589546902000},{"name":"DdlyGowther","changedToAt":1592602764000},{"name":"sinful_angel","changedToAt":1627856252000}]