[{"name":"Morris_N"},{"name":"Swag_GAMER1","changedToAt":1435599926000},{"name":"Freddy_Gaming","changedToAt":1440234831000},{"name":"Golden_Hacker","changedToAt":1447786113000},{"name":"ZERO_sky","changedToAt":1450963365000},{"name":"MorrisNouwens","changedToAt":1457792833000},{"name":"YourKermit","changedToAt":1521886219000},{"name":"barzss","changedToAt":1555956841000},{"name":"FriedaReiss","changedToAt":1608379868000},{"name":"SC3RAM0UCHE","changedToAt":1613233813000},{"name":"slithic","changedToAt":1621079651000}]