[{"name":"minesancrafts370"},{"name":"Obieta_Ereri","changedToAt":1465621907000},{"name":"xItsNikki_","changedToAt":1468219492000},{"name":"outthearcher","changedToAt":1471119660000},{"name":"toonfulmemes","changedToAt":1475787700000},{"name":"xXSneakyPandaXx","changedToAt":1479023897000},{"name":"XxSneakyPandaxX","changedToAt":1483484318000},{"name":"sneakyypanda","changedToAt":1493504714000},{"name":"sneakyyfox","changedToAt":1497927592000},{"name":"RandAnonymous","changedToAt":1547597814000},{"name":"WaffleCum","changedToAt":1552078918000}]