[{"name":"legonerd112"},{"name":"ItsNeverOgre__","changedToAt":1424462250000},{"name":"legonerd112","changedToAt":1427739404000},{"name":"ScottEvans_","changedToAt":1431133604000},{"name":"Phenomenal_","changedToAt":1433875008000},{"name":"oh_hey","changedToAt":1437421411000},{"name":"Tyrone_Legstrong","changedToAt":1440273848000},{"name":"DJ__Khaled","changedToAt":1451715677000},{"name":"dankmeems","changedToAt":1458156192000},{"name":"M9Sapphire","changedToAt":1460770769000},{"name":"Retruhlicious","changedToAt":1463424982000},{"name":"kenwood_","changedToAt":1466098390000},{"name":"SandPaperC0ndoms","changedToAt":1475453191000},{"name":"SandPapercond0ms","changedToAt":1480093043000},{"name":"WordRefrence","changedToAt":1489281943000},{"name":"Zxens","changedToAt":1491885103000},{"name":"KneeGrowPvP","changedToAt":1495396315000},{"name":"exboxone","changedToAt":1505683205000},{"name":"Woesner","changedToAt":1515429562000},{"name":"SamsWelfareCheck","changedToAt":1519002360000},{"name":"Woesner","changedToAt":1524010617000},{"name":"SamsWelfareCheck","changedToAt":1530850246000},{"name":"legonerd112","changedToAt":1555517482000}]