[{"name":"jumpedtuna202"},{"name":"PECGAMER","changedToAt":1480610598000},{"name":"Bibi_E","changedToAt":1483755186000},{"name":"pecgamerbr","changedToAt":1486393969000},{"name":"Pecgamer","changedToAt":1489950865000},{"name":"PECGAMER","changedToAt":1492563761000},{"name":"pecgamer_br","changedToAt":1497922447000},{"name":"PECGAMER","changedToAt":1500995069000},{"name":"hxype","changedToAt":1584925798000},{"name":"PECGAMER","changedToAt":1587659776000},{"name":"PeecXd","changedToAt":1593455411000}]