[{"name":"MrBiscuit51"},{"name":"KindeR_Pinguins","changedToAt":1491152049000},{"name":"TunMaladeBernard","changedToAt":1548858928000},{"name":"Cuitochette_","changedToAt":1552122531000},{"name":"dr5jmRedniKtx1dn","changedToAt":1555016816000},{"name":"Cuitochette_","changedToAt":1557610101000},{"name":"ChezSosh","changedToAt":1561152949000},{"name":"Cuitochette_","changedToAt":1564239602000},{"name":"_apisdn","changedToAt":1566918115000},{"name":"Choixpeau","changedToAt":1569605673000},{"name":"BanDeFuncraftRIP","changedToAt":1579280131000},{"name":"CaVaEtreToutNoir","changedToAt":1581872179000},{"name":"RestezChezVous","changedToAt":1585048230000},{"name":"Choixpeau","changedToAt":1587755243000},{"name":"Choipokemon","changedToAt":1603393340000},{"name":"Choixpeau","changedToAt":1606061616000},{"name":"OggyEtLesCafards","changedToAt":1613071582000},{"name":"Choixpeau","changedToAt":1615665219000},{"name":"TheorieDuComplot","changedToAt":1618257304000},{"name":"Choixpeau","changedToAt":1620850494000},{"name":"Enzo1958","changedToAt":1625516348000},{"name":"Choixpeau","changedToAt":1628108922000},{"name":"HAhHahAhAaahAHha","changedToAt":1640705212897},{"name":"Choixpeau","changedToAt":1643297786936},{"name":"YvanMonka","changedToAt":1645894045299},{"name":"Choixpeau","changedToAt":1648832120143},{"name":"EncoreDansUnJump","changedToAt":1659126181837},{"name":"Choixpeau","changedToAt":1661782988592}]