[{"name":"jackcyborg23"},{"name":"JackBedWars","changedToAt":1515015124000},{"name":"OkThenn","changedToAt":1517667193000},{"name":"Subscribeeee","changedToAt":1520341236000},{"name":"SoundLikeSkeppy","changedToAt":1522960815000},{"name":"Firr","changedToAt":1525618165000},{"name":"JPVlogs","changedToAt":1528226120000},{"name":"JPVlogsYT","changedToAt":1530880860000},{"name":"JPVlogsYTSpAsM","changedToAt":1533817564000},{"name":"JPVlogs","changedToAt":1536496185000},{"name":"RankedBoy80","changedToAt":1539214726000},{"name":"JackEP","changedToAt":1541941492000},{"name":"Op_JPGamezYT_DAB","changedToAt":1544568137000},{"name":"JPGamezYT","changedToAt":1547245146000},{"name":"pabr","changedToAt":1559160133000},{"name":"JPGamezYT","changedToAt":1561904987000},{"name":"MineProJP","changedToAt":1591628863000},{"name":"JPGamezYT","changedToAt":1594314155000},{"name":"MineProJP","changedToAt":1597704221000},{"name":"JPVlogsYT","changedToAt":1600349994000},{"name":"JPVlogss","changedToAt":1614633732000}]