[{"name":"Linede"},{"name":"Cozi_","changedToAt":1424380719000},{"name":"Cooozi","changedToAt":1429733950000},{"name":"Linede","changedToAt":1434383110000},{"name":"EmpereurDuSal_","changedToAt":1473956587000},{"name":"XIJOIN","changedToAt":1476616561000},{"name":"Linede","changedToAt":1480765701000},{"name":"Costefa","changedToAt":1485376102000},{"name":"Doi2PiedEcartez","changedToAt":1490519023000},{"name":"ZekyCheat","changedToAt":1493151971000},{"name":"KarmaKomaa","changedToAt":1495747666000},{"name":"Costefa","changedToAt":1500981041000},{"name":"Kencos","changedToAt":1587503789000}]