[{"name":"DillyChilly"},{"name":"YoutubeDillyyy","changedToAt":1598401228000},{"name":"DillySimpsTechno","changedToAt":1601229698000},{"name":"YoutubeDillyyy","changedToAt":1612139076000},{"name":"ProfessorYogurt","changedToAt":1625586955000},{"name":"ProfessorGoGurt","changedToAt":1629066610000},{"name":"YogurtIsVibin","changedToAt":1631994878569},{"name":"TheCopperFBI_","changedToAt":1634689356041},{"name":"ProfessorDilbert","changedToAt":1637848679305},{"name":"L0gan33","changedToAt":1658539257891}]