[{"name":"prokiller2006"},{"name":"XXXadithekingXXX","changedToAt":1423552717000},{"name":"adi5151","changedToAt":1426330458000},{"name":"ItsAdiGaming","changedToAt":1429342774000},{"name":"superkiller2015","changedToAt":1434830700000},{"name":"Elegantkoala1","changedToAt":1440070661000},{"name":"thekiller5500","changedToAt":1443199220000},{"name":"adibiti123","changedToAt":1453646263000},{"name":"Cookieman15","changedToAt":1457804998000},{"name":"P3nk_B3ar","changedToAt":1461235870000},{"name":"MinecraftgayNigg","changedToAt":1568037207000},{"name":"ArmaniGucciCK","changedToAt":1572191998000}]