[{"name":"AmrRBasha"},{"name":"Amr_GWA2C","changedToAt":1423053104000},{"name":"_DerpyBoy_","changedToAt":1432914853000},{"name":"_MrPenguin","changedToAt":1435789826000},{"name":"AmrPlayz","changedToAt":1438452817000},{"name":"Diamond_Miner_15","changedToAt":1441799147000},{"name":"_Sir_Slender_","changedToAt":1445184989000},{"name":"AmrPlayz","changedToAt":1451137158000},{"name":"Sir_Derpy_","changedToAt":1454341815000},{"name":"Amro_DP","changedToAt":1459783417000},{"name":"Sir__Toast","changedToAt":1464277301000},{"name":"Noodles_Creeper","changedToAt":1466881275000},{"name":"Donut_Agent","changedToAt":1469484414000},{"name":"Amro_Donut","changedToAt":1472850973000},{"name":"AlSaffah99","changedToAt":1497649735000},{"name":"Gloomy_Potato","changedToAt":1507912824000},{"name":"Mr_Ditto","changedToAt":1510587653000},{"name":"Nuggetx","changedToAt":1515259532000},{"name":"Agent_Pistachio","changedToAt":1518007468000},{"name":"Pistachiologist","changedToAt":1521735797000},{"name":"Amro_DP","changedToAt":1528598780000},{"name":"Nerdy_Stars","changedToAt":1534329659000},{"name":"Cakii_","changedToAt":1539441462000},{"name":"Cakiiz","changedToAt":1543676062000},{"name":"Amro_DP","changedToAt":1557801109000},{"name":"thiqqy","changedToAt":1561218055000}]