[{"name":"HenriqueArdigo"},{"name":"_MarcioHenrique","changedToAt":1471716434000},{"name":"M1STIC_PL4YS","changedToAt":1477588280000},{"name":"Marcio_PvP","changedToAt":1480439992000},{"name":"OPandaPlay02","changedToAt":1486424389000},{"name":"Bitel","changedToAt":1489366856000},{"name":"SrBitel","changedToAt":1491999099000},{"name":"Bitel_","changedToAt":1511311453000},{"name":"SrBitel","changedToAt":1514044214000},{"name":"Biteel","changedToAt":1525579496000},{"name":"feinhu","changedToAt":1531447611000}]