[{"name":"DylanDC14"},{"name":"DyLaNd015","changedToAt":1437150124000},{"name":"Dylando","changedToAt":1445714750000},{"name":"AnnaFanBoy","changedToAt":1449093085000},{"name":"DylanDo","changedToAt":1451751342000},{"name":"iHateMyselfs","changedToAt":1464963581000},{"name":"DylanDo","changedToAt":1467569176000},{"name":"Dylam","changedToAt":1472332231000},{"name":"DylanDo","changedToAt":1475327652000},{"name":"iWantYourBooty","changedToAt":1483281132000},{"name":"DylanDo","changedToAt":1485877522000},{"name":"DylanLovesAnna","changedToAt":1497366708000},{"name":"DylanDo","changedToAt":1500479098000},{"name":"DylanDC","changedToAt":1505176267000},{"name":"DylanDC14","changedToAt":1516231638000},{"name":"DylanDo","changedToAt":1538683376000},{"name":"DylanDC14","changedToAt":1545939769000},{"name":"DylanDo","changedToAt":1552225735000},{"name":"DylanDC14","changedToAt":1557576252000}]