[{"name":"xNanami"},{"name":"_Meryy_","changedToAt":1572682946000},{"name":"Marisha_qwp","changedToAt":1580849009000},{"name":"_Mangle_The_Fox_","changedToAt":1586029684000},{"name":"Pasteliaa_Korea","changedToAt":1590080005000},{"name":"Chacked_Chacked_","changedToAt":1593559839000},{"name":"charatopic","changedToAt":1597261706000},{"name":"_Your_Waifu","changedToAt":1603488008000},{"name":"FroggieRushii","changedToAt":1614291719000},{"name":"ShiN3ly","changedToAt":1616973124000},{"name":"DreamiCieZJe","changedToAt":1619628227000},{"name":"GreaterDog","changedToAt":1623149219000}]