[{"name":"FabCookie"},{"name":"71ny7ur7137175","changedToAt":1458767119000},{"name":"HazeNoAmami","changedToAt":1463025759000},{"name":"JenjyX","changedToAt":1488830569000},{"name":"BassAss","changedToAt":1500929571000},{"name":"lifeisgay","changedToAt":1505303541000},{"name":"creativenamehere","changedToAt":1508584933000},{"name":"TonyTortleTots","changedToAt":1571384397000},{"name":"_Alien_Jesus_","changedToAt":1579932283000},{"name":"Poopyhead12321","changedToAt":1587001012000},{"name":"Electrocreeperz","changedToAt":1604270602000},{"name":"DoorQueen","changedToAt":1609844818000},{"name":"Arkaic_Yelo","changedToAt":1649898425986}]