[{"name":"AlphaRamuse"},{"name":"MooJangX","changedToAt":1513715654000},{"name":"iiFrostix","changedToAt":1533295436000},{"name":"Snowwii","changedToAt":1544884530000},{"name":"cerns","changedToAt":1554946906000},{"name":"Snowwii","changedToAt":1560088186000},{"name":"Sqwush","changedToAt":1562707985000},{"name":"cerns","changedToAt":1565301219000},{"name":"doeo","changedToAt":1569773118000},{"name":"xmacerns","changedToAt":1574961033000},{"name":"Snowwii","changedToAt":1583693312000},{"name":"rqinn","changedToAt":1586287157000},{"name":"cernsie","changedToAt":1588882193000},{"name":"cqrns","changedToAt":1593016823000},{"name":"XXG4M3R_CERBSXX","changedToAt":1599499980000},{"name":"xmacerns","changedToAt":1602438325000},{"name":"cernsie","changedToAt":1608135544000}]