[{"name":"NoSkillNoKill11"},{"name":"Elky11","changedToAt":1561655607000},{"name":"lilElky","changedToAt":1568383786000},{"name":"lilelky","changedToAt":1575658295000},{"name":"socutekoalas","changedToAt":1582207169000},{"name":"lilelky","changedToAt":1584872234000},{"name":"eelky","changedToAt":1588274219000},{"name":"elkv","changedToAt":1596268681000},{"name":"daddyelki","changedToAt":1606385253000},{"name":"elkidatoxic","changedToAt":1610039620000},{"name":"aelki","changedToAt":1617282349000},{"name":"elkwi","changedToAt":1634390103000},{"name":"voisk","changedToAt":1646502007000},{"name":"cavay","changedToAt":1649873603553}]