[{"name":"DarkShroud15336"},{"name":"Kurt_Cobain","changedToAt":1423098138000},{"name":"IAmIlluminati","changedToAt":1425739497000},{"name":"Planetesimal","changedToAt":1428533860000},{"name":"iBeaturscores","changedToAt":1431733492000},{"name":"NebulaGuardian","changedToAt":1436938679000},{"name":"MCProSurvivalist","changedToAt":1439755703000},{"name":"HackerBuster","changedToAt":1450688686000},{"name":"Boxxed","changedToAt":1458177910000},{"name":"BrainFever","changedToAt":1472866336000},{"name":"YourLifeIsOver","changedToAt":1475573625000},{"name":"NoMacrosHereBud","changedToAt":1496995704000},{"name":"Jookeh","changedToAt":1499614496000},{"name":"BannedOnServer","changedToAt":1513432327000}]