[{"name":"xXLauriXx"},{"name":"byFlobby","changedToAt":1457293721000},{"name":"FxbiiOP","changedToAt":1470495057000},{"name":"coolerfxbiii","changedToAt":1473521480000},{"name":"KannKeinSport_","changedToAt":1476126710000},{"name":"lePremaex","changedToAt":1479069920000},{"name":"SiiR0_","changedToAt":1481718074000},{"name":"Hot_SiiR0","changedToAt":1484407124000},{"name":"5g764j50897uj98h","changedToAt":1487099197000},{"name":"Cuteey","changedToAt":1489938488000},{"name":"CuteeyFanboy","changedToAt":1492891398000},{"name":"MVP_Fanboy","changedToAt":1524940476000},{"name":"NotCuteey","changedToAt":1529069164000},{"name":"SAS_ManKenntSich","changedToAt":1537634646000},{"name":"SIR0","changedToAt":1540285832000},{"name":"LoomHamerV2","changedToAt":1542930796000},{"name":"LoomUpgrade","changedToAt":1547479351000},{"name":"Questionist","changedToAt":1550227800000},{"name":"WarzoneRocket","changedToAt":1553451533000},{"name":"GARD420","changedToAt":1594737968000},{"name":"Ronin_445","changedToAt":1605178939000}]