[{"name":"GIANT_BUTTER2"},{"name":"YourlocalDuck","changedToAt":1440034104000},{"name":"RoccoPlayz_MC","changedToAt":1442674350000},{"name":"El_Preston","changedToAt":1445376871000},{"name":"PsyhoPleb","changedToAt":1447978371000},{"name":"Buzz_Man118","changedToAt":1450627966000},{"name":"Minecraft_Jamer8","changedToAt":1453659063000},{"name":"MyHackAlt101","changedToAt":1457284535000},{"name":"Huawhi2","changedToAt":1461966083000},{"name":"Nube10101","changedToAt":1498497499000},{"name":"IM_A_GOD12","changedToAt":1509853724000},{"name":"saucy_002YT","changedToAt":1513918532000},{"name":"YoSaucy","changedToAt":1516670317000}]