[{"name":"FrothierDeer"},{"name":"_FasTCekcU_","changedToAt":1450183121000},{"name":"JuxFreak","changedToAt":1452775359000},{"name":"Ivanxa4","changedToAt":1497020910000},{"name":"JuxFreak","changedToAt":1500202869000},{"name":"TMCTC","changedToAt":1503499420000},{"name":"LoveCAJIO","changedToAt":1506249123000},{"name":"WaileeMyGirl","changedToAt":1509818059000},{"name":"VanyaSexStar","changedToAt":1516373134000},{"name":"IvanDura4ok","changedToAt":1529178377000},{"name":"Saloed3000","changedToAt":1657367863034},{"name":"MegaKilller2012","changedToAt":1661552088037}]