[{"name":"bad_fartX_X12"},{"name":"FlashCraft127","changedToAt":1428029173000},{"name":"FlashFalconsRush","changedToAt":1433659594000},{"name":"FlashCraft127","changedToAt":1436300108000},{"name":"Solar_Flash","changedToAt":1458867968000},{"name":"OPCALIFORNIAN","changedToAt":1538968775000},{"name":"Marc1nho","changedToAt":1570082420000},{"name":"MarcoAsensio","changedToAt":1572674545000},{"name":"Hazaard","changedToAt":1575272157000},{"name":"xSoleill","changedToAt":1604596398000},{"name":"Solxeil","changedToAt":1607208821000}]