[{"name":"DoctorMeerkat27"},{"name":"TheMonDavid","changedToAt":1425144618000},{"name":"Aids_HDGaming","changedToAt":1453768888000},{"name":"Aidscc","changedToAt":1504283107000},{"name":"Tyroneeeeee","changedToAt":1586129819000},{"name":"zDetermined","changedToAt":1588837877000},{"name":"Lucifierv","changedToAt":1591489491000},{"name":"HARDHOME","changedToAt":1595107450000},{"name":"BLACKANDCHINESE","changedToAt":1597703050000},{"name":"DavidClean","changedToAt":1600563638000},{"name":"InjectedCC","changedToAt":1603161563000},{"name":"ASAPM0B","changedToAt":1606100613000},{"name":"Tyroneeeeee","changedToAt":1611428262000},{"name":"OriginalGangMan3","changedToAt":1614407546000},{"name":"flackito","changedToAt":1617052460000},{"name":"SlippinJimmyy","changedToAt":1658208655485},{"name":"flackito","changedToAt":1660808172335}]