[{"name":"CookieDerpCraft"},{"name":"DerpyAustralian","changedToAt":1439039167000},{"name":"YandereChan666","changedToAt":1457434352000},{"name":"derpyaustralian","changedToAt":1460203869000},{"name":"PastelizedEmo","changedToAt":1462875459000},{"name":"Pxstelized","changedToAt":1465820982000},{"name":"EmoFlop","changedToAt":1468742749000},{"name":"pxstelized","changedToAt":1471340584000},{"name":"GayShips","changedToAt":1489921251000},{"name":"tumblrsam","changedToAt":1495380131000},{"name":"saltyuwu","changedToAt":1538382725000},{"name":"SHNORPY","changedToAt":1611848788000}]