[{"name":"CharmLovesMC"},{"name":"CharmUnicornz","changedToAt":1423589950000},{"name":"CharziMarzi","changedToAt":1451825269000},{"name":"charzimarzi","changedToAt":1497100799000},{"name":"chxrminn","changedToAt":1502823282000},{"name":"chxrmane","changedToAt":1506019503000},{"name":"jhoep","changedToAt":1514086509000},{"name":"BONCHONN","changedToAt":1516992197000},{"name":"chxrmane","changedToAt":1519717022000},{"name":"jhoep","changedToAt":1522683276000},{"name":"chrmss","changedToAt":1563023155000},{"name":"chrmin","changedToAt":1565773421000},{"name":"CHIERM","changedToAt":1587936997000},{"name":"chermin","changedToAt":1590847482000},{"name":"mrfatboomie","changedToAt":1595955528000},{"name":"chrmin","changedToAt":1599939286000}]