[{"name":"YoungSvge"},{"name":"Slim_Shaney","changedToAt":1487975720000},{"name":"SlimRambe","changedToAt":1495661941000},{"name":"SlimRambeYT","changedToAt":1501857717000},{"name":"QuackleyYT","changedToAt":1504455366000},{"name":"S_S_G","changedToAt":1507238919000},{"name":"IGivLs","changedToAt":1513878067000},{"name":"Night_Stlker","changedToAt":1516559568000},{"name":"1noccnetTV","changedToAt":1568329027000},{"name":"breezzilyTV","changedToAt":1585934014000},{"name":"TonyGe","changedToAt":1591395611000},{"name":"Breezi1y","changedToAt":1594746601000},{"name":"MouseyTheMick","changedToAt":1609300188000},{"name":"ShaneGiffordOG","changedToAt":1613246153000}]