[{"name":"TokyoPanda"},{"name":"desupanda","changedToAt":1440037774000},{"name":"pandaplushiee","changedToAt":1446943394000},{"name":"Cresendo01","changedToAt":1450975404000},{"name":"Lunaxrisz","changedToAt":1478458916000},{"name":"LunaGalaxia","changedToAt":1488931274000},{"name":"AriaaRose","changedToAt":1495392528000},{"name":"xXBunnieXx","changedToAt":1505410856000},{"name":"Fqte_","changedToAt":1508544697000},{"name":"Junqkook_","changedToAt":1513205275000},{"name":"Kooqi","changedToAt":1516316961000},{"name":"Xivhy","changedToAt":1563069061000}]