[{"name":"lucyed"},{"name":"lucy1199","changedToAt":1543326193000},{"name":"Royal_cat421_tw","changedToAt":1546053541000},{"name":"_Purgatory333_tw","changedToAt":1551509707000},{"name":"blue_dragonfly33","changedToAt":1554118005000},{"name":"Zhezhe_TW2333","changedToAt":1557063969000},{"name":"Zhezhe_TW_YEE","changedToAt":1560436782000},{"name":"Winter_dust_TW","changedToAt":1570347669000},{"name":"TW_YMK","changedToAt":1583658703000},{"name":"GD_YMK_TW","changedToAt":1591440373000},{"name":"GD_Zhe_TW","changedToAt":1598011202000},{"name":"GD_douob_tw","changedToAt":1602165811000},{"name":"GD_Zhe_TW","changedToAt":1606016909000},{"name":"zhe04_21tw","changedToAt":1610874965000},{"name":"zhe_04_21_tw","changedToAt":1613481202000},{"name":"zhe04_21tw","changedToAt":1618903053000},{"name":"Sakura_TW","changedToAt":1625570866000},{"name":"Ahoooooooy","changedToAt":1631019788000},{"name":"Ahoy_","changedToAt":1633744034512},{"name":"Roxye_","changedToAt":1636878054508},{"name":"_Dongcheng","changedToAt":1645441642373},{"name":"Doncheng_","changedToAt":1655623069469}]