[{"name":"XXCHagXX"},{"name":"KaroIMaKlocka","changedToAt":1424006652000},{"name":"ChaGoVskyy","changedToAt":1428175068000},{"name":"Paula124x","changedToAt":1433707221000},{"name":"JustinBiber","changedToAt":1437828042000},{"name":"KiiTTyKat1337","changedToAt":1440860560000},{"name":"RuchamMatkeTopik","changedToAt":1444566151000},{"name":"Br0Ky","changedToAt":1448044896000},{"name":"NaTkaa","changedToAt":1451165400000},{"name":"autumnKiss","changedToAt":1465658401000},{"name":"kiniaxv","changedToAt":1602669227000},{"name":"Kiniaxvv","changedToAt":1609969932000}]