[{"name":"HeroGamer123"},{"name":"EnderGaming14","changedToAt":1463873274000},{"name":"Its_Ender1","changedToAt":1466549394000},{"name":"Its_Cereal","changedToAt":1476382701000},{"name":"Casper15","changedToAt":1491768989000},{"name":"AsapDaddy","changedToAt":1495241442000},{"name":"_BabyDaddy_","changedToAt":1498010718000},{"name":"McChild","changedToAt":1502135444000},{"name":"Tay_k_","changedToAt":1506641940000},{"name":"McChild","changedToAt":1513033060000},{"name":"9rl","changedToAt":1515638243000},{"name":"Tbr_","changedToAt":1604002651000}]