[{"name":"GabiKing1k"},{"name":"TheSuper_mario","changedToAt":1491806987000},{"name":"Laztok_2Blu3chaw","changedToAt":1494515609000},{"name":"LazTok_V2GabiPro","changedToAt":1497274381000},{"name":"Its_Gabi","changedToAt":1499954056000},{"name":"BolBol_Pro","changedToAt":1513861815000},{"name":"_Gabriel11_","changedToAt":1561961157000},{"name":"__Poki__","changedToAt":1567020871000},{"name":"BolBol_Pro","changedToAt":1570971492000},{"name":"_Gobzi","changedToAt":1573756428000},{"name":"_Antetokounmpo34","changedToAt":1598095062000},{"name":"_DeniAvdija9_","changedToAt":1608064662000}]