[{"name":"DerMax12212"},{"name":"_Zynox_","changedToAt":1462042324000},{"name":"SkyStylerHD","changedToAt":1464649897000},{"name":"LentoxPL","changedToAt":1468061481000},{"name":"DarkPandaPL","changedToAt":1470924489000},{"name":"CuzImGoku","changedToAt":1473547031000},{"name":"LeqitOm4r","changedToAt":1476474501000},{"name":"GohanSSJBlue","changedToAt":1480158822000},{"name":"VamroxGHG","changedToAt":1482956759000},{"name":"TrunksSSJBCSGO","changedToAt":1485809842000},{"name":"FreazonPL","changedToAt":1492390094000},{"name":"Leo12212","changedToAt":1497050145000},{"name":"Omar12212","changedToAt":1499911369000},{"name":"DarkLentoxYT","changedToAt":1502587647000},{"name":"BraunerTeddyBaer","changedToAt":1505490748000},{"name":"HeyOmarTV","changedToAt":1508109052000},{"name":"DarkLimet","changedToAt":1510931766000},{"name":"AscalterFan03","changedToAt":1514682909000},{"name":"HabeNurGucci","changedToAt":1517701422000},{"name":"Aqfel","changedToAt":1525115560000},{"name":"DarkLimitYT","changedToAt":1527761458000},{"name":"14pm","changedToAt":1533561869000},{"name":"Darkiiix","changedToAt":1536859279000},{"name":"DarkLimitYT","changedToAt":1539478284000},{"name":"EinDarklimit","changedToAt":1546602088000},{"name":"DarklimitYT","changedToAt":1552142203000},{"name":"ThaaRamo","changedToAt":1555685283000},{"name":"DarkLimitYT","changedToAt":1559971450000},{"name":"limitbtw","changedToAt":1577432049000},{"name":"hxssliger","changedToAt":1596652520000},{"name":"limit07","changedToAt":1604781210000},{"name":"limituwu","changedToAt":1648673022698}]